xrayscatteringtools/__init__.py
xrayscatteringtools/epicsArch.py
xrayscatteringtools/io.py
xrayscatteringtools/plotting.py
xrayscatteringtools/utils.py
xrayscatteringtools/calib/__init__.py
xrayscatteringtools/calib/geometry_calibration.py
xrayscatteringtools/calib/masking.py
xrayscatteringtools/calib/scattering_corrections.py
xrayscatteringtools/calib/data/Zn_attenuation_length.h5
xrayscatteringtools/data/Jungfrau4M.h5
xrayscatteringtools/theory/__init__.py
xrayscatteringtools/theory/geometries.py
xrayscatteringtools/theory/geometries.pyi
xrayscatteringtools/theory/iam.py
xrayscatteringtools/theory/patterns.py
xrayscatteringtools/theory/patterns.pyi
xrayscatteringtools/theory/data/IAM/Compton_Factors.npy
xrayscatteringtools/theory/data/IAM/Scattering_Factors.npy
xrayscatteringtools/theory/data/geometries/SF6__CCSD_T_DHK__aug_cc_pV5Z_DK.h5
xrayscatteringtools/theory/data/geometries/make_geometry_h5.py
xrayscatteringtools/theory/data/patterns/SF6__CCSD__aug_cc_pVDZ.h5
xrayscatteringtools/theory/data/patterns/SF6__HF__aug_cc_pVDZ.h5
xrayscatteringtools/theory/data/patterns/SF6__MP2__aug_cc_pVDZ.h5
xrayscatteringtools/theory/data/patterns/convert_ab_initio_to_h5.py
xrayscatteringtools-0.3.0.dist-info/METADATA
xrayscatteringtools-0.3.0.dist-info/WHEEL
xrayscatteringtools-0.3.0.dist-info/licenses/LICENSE
xrayscatteringtools-0.3.0.dist-info/RECORD
