Metadata-Version: 2.4
Name: xrayscatteringtools
Version: 0.3.0
Summary: A library for gas phase analysis at the CXI endstation
Project-URL: Homepage, https://github.com/Weber-Group/xrayscatteringtools
Project-URL: Issues, https://github.com/Weber-Group/xrayscatteringtools/issues
Author-email: David Romano <david_j_romano@brown.edu>
License-Expression: MIT
License-File: LICENSE
Requires-Python: >=3.9
Requires-Dist: h5py
Requires-Dist: ipython
Requires-Dist: matplotlib
Requires-Dist: numpy<2
Requires-Dist: pathlib
Requires-Dist: pyyaml
Requires-Dist: requests
Requires-Dist: scipy>=1.11
Requires-Dist: tqdm
Requires-Dist: xraylib
Provides-Extra: dev
Requires-Dist: black>=24.0; extra == 'dev'
Requires-Dist: mypy>=1.9; extra == 'dev'
Requires-Dist: pytest>=8.0; extra == 'dev'
Requires-Dist: ruff>=0.3; extra == 'dev'
